clovers_client/config.py
clovers_client/console/adapter/__init__.py
clovers_client/console/adapter/adapter.py
clovers_client/console/adapter/config.py
clovers_client/console/client/__init__.py
clovers_client/console/client/client.py
clovers_client/console/client/config.py
clovers_client/console/client/console.py
clovers_client/console/event.py
clovers_client/logger.py
clovers_client/onebot/v11/adapter/__init__.py
clovers_client/onebot/v11/adapter/adapter.py
clovers_client/onebot/v11/adapter/config.py
clovers_client/onebot/v11/adapter/typing.py
clovers_client/onebot/v11/client/__init__.py
clovers_client/onebot/v11/client/client.py
clovers_client/onebot/v11/client/config.py
clovers_client/qq/adapters/config.py
clovers_client/qq/adapters/group.py
clovers_client/qq/adapters/guild.py
clovers_client/qq/adapters/typing.py
clovers_client/qq/client/__init__.py
clovers_client/qq/client/client.py
clovers_client/qq/client/config.py
clovers_client-0.0.3.dist-info/LICENSE
clovers_client-0.0.3.dist-info/METADATA
clovers_client-0.0.3.dist-info/WHEEL
clovers_client-0.0.3.dist-info/RECORD
