Metadata-Version: 2.3
Name: clovers-client
Version: 0.0.3
Summary: 
Author: KarisAya
Author-email: karisaya@foxmail.com
Requires-Python: >=3.12,<4.0.0
Classifier: Programming Language :: Python :: 3
Classifier: Programming Language :: Python :: 3.12
Classifier: Programming Language :: Python :: 3.13
Provides-Extra: console
Provides-Extra: onebot
Provides-Extra: qq
Requires-Dist: clovers (>=0.4.8,<1.0.0)
Requires-Dist: httpx (>=0.23.1,<1.0.0) ; extra == "onebot"
Requires-Dist: pillow (>=11.1.0,<12.0.0) ; extra == "console"
Requires-Dist: pydantic (>=2.10.6,<3.0.0) ; extra == "console"
Requires-Dist: pydantic (>=2.10.6,<3.0.0) ; extra == "onebot"
Requires-Dist: pydantic (>=2.10.6,<3.0.0) ; extra == "qq"
Requires-Dist: qq-botpy (>=1.2.1,<2.0.0) ; extra == "qq"
Requires-Dist: websockets (>=15.0.0,<16.0.0) ; extra == "console"
Requires-Dist: websockets (>=15.0.0,<16.0.0) ; extra == "onebot"
